{"spec":{"id":"gt-bigword-newgame","industry":"电竞游戏","channel":"社群朋友圈","material":"方形海报","title":"开服","style":"big-word"},"attributions":[],"document":{"id":"design-gt-bigword-newgame-qcak8k","title":"开服","width":1080,"height":1080,"background":{"gradient":"linear-gradient(155deg, #0b0f1a, #111827)","opacity":1,"overlay":"grid","overlayColor":"#22d3ee","overlayOpacity":0.08},"elements":[{"id":"shape-qcak8k-1","type":"shape","x":0,"y":0,"w":1080,"h":1080,"rotation":0,"z":1,"locked":false,"opacity":1,"props":{"kind":"rect","fill":"linear-gradient(160deg, #0b0f1a, #111827)","stroke":"transparent","strokeWidth":0,"radius":0}},{"id":"shape-qcak8k-2","type":"shape","x":-23.412792494656884,"y":437.7330151316025,"w":380.3222299972187,"h":380.3222299972187,"rotation":0,"z":2,"locked":false,"opacity":0.655077177544626,"props":{"kind":"circle","fill":"#f472b6","stroke":"transparent","strokeWidth":0,"radius":0}},{"id":"shape-qcak8k-10","type":"shape","x":626.4,"y":-162,"w":648,"h":648,"rotation":0,"z":2,"locked":false,"opacity":0.2,"props":{"kind":"circle","fill":"#f472b6","stroke":"transparent","strokeWidth":0,"radius":0}},{"id":"shape-qcak8k-3","type":"shape","x":128.74854059965756,"y":-1.3500411661667613,"w":636.4779256875057,"h":636.4779256875057,"rotation":0,"z":3,"locked":false,"opacity":0.5791611824553279,"props":{"kind":"circle","fill":"#1f2937","stroke":"transparent","strokeWidth":0,"radius":0}},{"id":"shape-qcak8k-5","type":"shape","x":43.2,"y":64.8,"w":8.64,"h":8.64,"rotation":0,"z":3,"locked":false,"opacity":0.14,"props":{"kind":"circle","fill":"#22d3ee","stroke":"transparent","strokeWidth":0,"radius":0}},{"id":"shape-qcak8k-6","type":"shape","x":91.80000000000001,"y":64.8,"w":8.64,"h":8.64,"rotation":0,"z":3,"locked":false,"opacity":0.14,"props":{"kind":"circle","fill":"#22d3ee","stroke":"transparent","strokeWidth":0,"radius":0}},{"id":"shape-qcak8k-7","type":"shape","x":140.4,"y":64.8,"w":8.64,"h":8.64,"rotation":0,"z":3,"locked":false,"opacity":0.14,"props":{"kind":"circle","fill":"#22d3ee","stroke":"transparent","strokeWidth":0,"radius":0}},{"id":"shape-qcak8k-8","type":"shape","x":189,"y":64.8,"w":8.64,"h":8.64,"rotation":0,"z":3,"locked":false,"opacity":0.14,"props":{"kind":"circle","fill":"#22d3ee","stroke":"transparent","strokeWidth":0,"radius":0}},{"id":"shape-qcak8k-9","type":"shape","x":43.2,"y":113.4,"w":8.64,"h":8.64,"rotation":0,"z":3,"locked":false,"opacity":0.14,"props":{"kind":"circle","fill":"#22d3ee","stroke":"transparent","strokeWidth":0,"radius":0}},{"id":"shape-qcak8k-a","type":"shape","x":91.80000000000001,"y":113.4,"w":8.64,"h":8.64,"rotation":0,"z":3,"locked":false,"opacity":0.14,"props":{"kind":"circle","fill":"#22d3ee","stroke":"transparent","strokeWidth":0,"radius":0}},{"id":"shape-qcak8k-b","type":"shape","x":140.4,"y":113.4,"w":8.64,"h":8.64,"rotation":0,"z":3,"locked":false,"opacity":0.14,"props":{"kind":"circle","fill":"#22d3ee","stroke":"transparent","strokeWidth":0,"radius":0}},{"id":"shape-qcak8k-c","type":"shape","x":189,"y":113.4,"w":8.64,"h":8.64,"rotation":0,"z":3,"locked":false,"opacity":0.14,"props":{"kind":"circle","fill":"#22d3ee","stroke":"transparent","strokeWidth":0,"radius":0}},{"id":"shape-qcak8k-d","type":"shape","x":43.2,"y":162,"w":8.64,"h":8.64,"rotation":0,"z":3,"locked":false,"opacity":0.14,"props":{"kind":"circle","fill":"#22d3ee","stroke":"transparent","strokeWidth":0,"radius":0}},{"id":"shape-qcak8k-e","type":"shape","x":91.80000000000001,"y":162,"w":8.64,"h":8.64,"rotation":0,"z":3,"locked":false,"opacity":0.14,"props":{"kind":"circle","fill":"#22d3ee","stroke":"transparent","strokeWidth":0,"radius":0}},{"id":"shape-qcak8k-f","type":"shape","x":140.4,"y":162,"w":8.64,"h":8.64,"rotation":0,"z":3,"locked":false,"opacity":0.14,"props":{"kind":"circle","fill":"#22d3ee","stroke":"transparent","strokeWidth":0,"radius":0}},{"id":"shape-qcak8k-g","type":"shape","x":189,"y":162,"w":8.64,"h":8.64,"rotation":0,"z":3,"locked":false,"opacity":0.14,"props":{"kind":"circle","fill":"#22d3ee","stroke":"transparent","strokeWidth":0,"radius":0}},{"id":"shape-qcak8k-h","type":"shape","x":842.4,"y":777.6,"w":8.64,"h":8.64,"rotation":0,"z":3,"locked":false,"opacity":0.14,"props":{"kind":"circle","fill":"#22d3ee","stroke":"transparent","strokeWidth":0,"radius":0}},{"id":"shape-qcak8k-i","type":"shape","x":891,"y":777.6,"w":8.64,"h":8.64,"rotation":0,"z":3,"locked":false,"opacity":0.14,"props":{"kind":"circle","fill":"#22d3ee","stroke":"transparent","strokeWidth":0,"radius":0}},{"id":"shape-qcak8k-j","type":"shape","x":939.6,"y":777.6,"w":8.64,"h":8.64,"rotation":0,"z":3,"locked":false,"opacity":0.14,"props":{"kind":"circle","fill":"#22d3ee","stroke":"transparent","strokeWidth":0,"radius":0}},{"id":"shape-qcak8k-k","type":"shape","x":988.2,"y":777.6,"w":8.64,"h":8.64,"rotation":0,"z":3,"locked":false,"opacity":0.14,"props":{"kind":"circle","fill":"#22d3ee","stroke":"transparent","strokeWidth":0,"radius":0}},{"id":"shape-qcak8k-l","type":"shape","x":842.4,"y":826.2,"w":8.64,"h":8.64,"rotation":0,"z":3,"locked":false,"opacity":0.14,"props":{"kind":"circle","fill":"#22d3ee","stroke":"transparent","strokeWidth":0,"radius":0}},{"id":"shape-qcak8k-m","type":"shape","x":891,"y":826.2,"w":8.64,"h":8.64,"rotation":0,"z":3,"locked":false,"opacity":0.14,"props":{"kind":"circle","fill":"#22d3ee","stroke":"transparent","strokeWidth":0,"radius":0}},{"id":"shape-qcak8k-n","type":"shape","x":939.6,"y":826.2,"w":8.64,"h":8.64,"rotation":0,"z":3,"locked":false,"opacity":0.14,"props":{"kind":"circle","fill":"#22d3ee","stroke":"transparent","strokeWidth":0,"radius":0}},{"id":"shape-qcak8k-o","type":"shape","x":988.2,"y":826.2,"w":8.64,"h":8.64,"rotation":0,"z":3,"locked":false,"opacity":0.14,"props":{"kind":"circle","fill":"#22d3ee","stroke":"transparent","strokeWidth":0,"radius":0}},{"id":"shape-qcak8k-p","type":"shape","x":842.4,"y":874.8000000000001,"w":8.64,"h":8.64,"rotation":0,"z":3,"locked":false,"opacity":0.14,"props":{"kind":"circle","fill":"#22d3ee","stroke":"transparent","strokeWidth":0,"radius":0}},{"id":"shape-qcak8k-q","type":"shape","x":891,"y":874.8000000000001,"w":8.64,"h":8.64,"rotation":0,"z":3,"locked":false,"opacity":0.14,"props":{"kind":"circle","fill":"#22d3ee","stroke":"transparent","strokeWidth":0,"radius":0}},{"id":"shape-qcak8k-r","type":"shape","x":939.6,"y":874.8000000000001,"w":8.64,"h":8.64,"rotation":0,"z":3,"locked":false,"opacity":0.14,"props":{"kind":"circle","fill":"#22d3ee","stroke":"transparent","strokeWidth":0,"radius":0}},{"id":"shape-qcak8k-s","type":"shape","x":988.2,"y":874.8000000000001,"w":8.64,"h":8.64,"rotation":0,"z":3,"locked":false,"opacity":0.14,"props":{"kind":"circle","fill":"#22d3ee","stroke":"transparent","strokeWidth":0,"radius":0}},{"id":"shape-qcak8k-t","type":"shape","x":842.4,"y":923.4000000000001,"w":8.64,"h":8.64,"rotation":0,"z":3,"locked":false,"opacity":0.14,"props":{"kind":"circle","fill":"#22d3ee","stroke":"transparent","strokeWidth":0,"radius":0}},{"id":"shape-qcak8k-u","type":"shape","x":891,"y":923.4000000000001,"w":8.64,"h":8.64,"rotation":0,"z":3,"locked":false,"opacity":0.14,"props":{"kind":"circle","fill":"#22d3ee","stroke":"transparent","strokeWidth":0,"radius":0}},{"id":"shape-qcak8k-v","type":"shape","x":939.6,"y":923.4000000000001,"w":8.64,"h":8.64,"rotation":0,"z":3,"locked":false,"opacity":0.14,"props":{"kind":"circle","fill":"#22d3ee","stroke":"transparent","strokeWidth":0,"radius":0}},{"id":"shape-qcak8k-w","type":"shape","x":988.2,"y":923.4000000000001,"w":8.64,"h":8.64,"rotation":0,"z":3,"locked":false,"opacity":0.14,"props":{"kind":"circle","fill":"#22d3ee","stroke":"transparent","strokeWidth":0,"radius":0}},{"id":"shape-qcak8k-4","type":"shape","x":326.51161312417673,"y":503.9685147831815,"w":664.6388033709669,"h":664.6388033709669,"rotation":0,"z":4,"locked":false,"opacity":0.7675969398895264,"props":{"kind":"circle","fill":"#22d3ee","stroke":"transparent","strokeWidth":0,"radius":0}},{"id":"shape-qcak8k-x","type":"shape","x":972,"y":108,"w":32.4,"h":32.4,"rotation":0,"z":4,"locked":false,"opacity":1,"props":{"kind":"sparkle","fill":"#f472b6","stroke":"transparent","strokeWidth":0,"radius":0}},{"id":"shape-qcak8k-y","type":"shape","x":64.8,"y":594,"w":25.92,"h":25.92,"rotation":0,"z":4,"locked":false,"opacity":1,"props":{"kind":"sparkle","fill":"#f472b6","stroke":"transparent","strokeWidth":0,"radius":0}},{"id":"shape-qcak8k-z","type":"shape","x":1004.4000000000001,"y":453.59999999999997,"w":21.6,"h":21.6,"rotation":0,"z":4,"locked":false,"opacity":1,"props":{"kind":"sparkle","fill":"#f472b6","stroke":"transparent","strokeWidth":0,"radius":0}},{"id":"image-qcak8k-11","type":"image","x":21.6,"y":21.6,"w":324,"h":324,"rotation":0,"z":6,"locked":false,"opacity":1,"props":{"src":"https://oceanleo-assets.oss-cn-guangzhou.aliyuncs.com/assets/image/design-deco/design-deco-sparkle-01.webp?x-oss-process=image/format,png","radius":0,"filter":"none","flipX":false,"flipY":false}},{"id":"image-qcak8k-12","type":"image","x":493.7577464788733,"y":194.4000000000001,"w":623.6619718309859,"h":885.5999999999999,"rotation":0,"z":8,"locked":false,"opacity":1,"props":{"src":"https://oceanleo-assets.oss-cn-guangzhou.aliyuncs.com/assets/image/design-object/design-obj-gamepad-01.webp?x-oss-process=image/format,png","radius":0,"filter":"none","flipX":false,"flipY":false,"dropShadow":"medium"}},{"id":"text-qcak8k-15","type":"text","x":59.4,"y":167.4,"w":509.76,"h":300.7023264,"rotation":0,"z":30,"locked":false,"opacity":1,"props":{"text":"开服","fontSize":270.1728,"color":"#22d3ee","fontFamily":"Smiley Sans","fontWeight":900,"fontStyle":"normal","lineHeight":1.06,"letterSpacing":1,"textAlign":"left","effect":"outline2","strokeColor":"#0b0f1a","strokeColor2":"#ffffff","strokeScale":0.04,"shadowColorHex":"rgba(8,145,178,0.32)"}},{"id":"shape-qcak8k-13","type":"shape","x":59.4,"y":81,"w":248,"h":68,"rotation":0,"z":39,"locked":false,"opacity":1,"props":{"kind":"rect","fill":"#22d3ee","stroke":"transparent","strokeWidth":0,"radius":34,"shadowPreset":"soft"}},{"id":"shape-qcak8k-19","type":"shape","x":59.4,"y":485.39699199999995,"w":509.76,"h":91.80000000000001,"rotation":0,"z":39,"locked":false,"opacity":1,"props":{"kind":"rect","fill":"#f0f9ff","stroke":"transparent","strokeWidth":0,"radius":12}},{"id":"shape-qcak8k-1b","type":"shape","x":59.4,"y":972,"w":208,"h":56,"rotation":0,"z":39,"locked":false,"opacity":1,"props":{"kind":"rect","fill":"rgba(255,255,255,0.72)","stroke":"transparent","strokeWidth":0,"radius":28}},{"id":"shape-qcak8k-1d","type":"shape","x":281.4,"y":972,"w":175.6,"h":56,"rotation":0,"z":39,"locked":false,"opacity":1,"props":{"kind":"rect","fill":"rgba(255,255,255,0.72)","stroke":"transparent","strokeWidth":0,"radius":28}},{"id":"text-qcak8k-14","type":"text","x":59.4,"y":95.8,"w":248,"h":41.6,"rotation":0,"z":40,"locked":false,"opacity":1,"props":{"text":"新游上线","fontSize":32,"color":"#ffffff","fontFamily":"Alibaba PuHuiTi","fontWeight":800,"fontStyle":"normal","lineHeight":1.12,"letterSpacing":0,"textAlign":"center","effect":"none"}},{"id":"text-qcak8k-1a","type":"text","x":59.4,"y":504.080992,"w":509.76,"h":58.968,"rotation":0,"z":40,"locked":false,"opacity":1,"props":{"text":"全新版本 · 登录送豪礼","fontSize":45.36,"color":"#1f2937","fontFamily":"Alibaba PuHuiTi","fontWeight":800,"fontStyle":"normal","lineHeight":1.12,"letterSpacing":0,"textAlign":"center","effect":"none"}},{"id":"text-qcak8k-1c","type":"text","x":59.4,"y":982.504,"w":208,"h":37.908,"rotation":0,"z":40,"locked":false,"opacity":1,"props":{"text":"登录领神装","fontSize":29.16,"color":"#f0f9ff","fontFamily":"Alibaba PuHuiTi","fontWeight":700,"fontStyle":"normal","lineHeight":1.12,"letterSpacing":0,"textAlign":"center","effect":"none"}},{"id":"text-qcak8k-1e","type":"text","x":281.4,"y":982.504,"w":175.6,"h":37.908,"rotation":0,"z":40,"locked":false,"opacity":1,"props":{"text":"首充双倍","fontSize":29.16,"color":"#f0f9ff","fontFamily":"Alibaba PuHuiTi","fontWeight":700,"fontStyle":"normal","lineHeight":1.12,"letterSpacing":0,"textAlign":"center","effect":"none"}},{"id":"shape-qcak8k-16","type":"shape","x":324.1530569230833,"y":217.6596719805035,"w":42.03745547104124,"h":42.03745547104124,"rotation":19.652882078500873,"z":46,"locked":false,"opacity":1,"props":{"kind":"sparkle","fill":"#f472b6","stroke":"transparent","strokeWidth":0,"radius":0}},{"id":"shape-qcak8k-17","type":"shape","x":176.35841162448173,"y":181.92328534482817,"w":28.17510561124182,"h":28.17510561124182,"rotation":1.5254341259251507,"z":46,"locked":false,"opacity":1,"props":{"kind":"sparkle","fill":"#f472b6","stroke":"transparent","strokeWidth":0,"radius":0}},{"id":"shape-qcak8k-18","type":"shape","x":190.22498576197862,"y":243.03554472374344,"w":29.759443559304987,"h":29.759443559304987,"rotation":5.575458596262829,"z":46,"locked":false,"opacity":1,"props":{"kind":"sparkle","fill":"#f472b6","stroke":"transparent","strokeWidth":0,"radius":0}}],"updatedAt":"2026-07-04T09:27:43.687Z"}}