{"spec":{"id":"mc-gzh-05","industry":"IT互联网","channel":"微信公众号","material":"公众号首图","title":"新品正式发布","style":"gzh-header"},"attributions":[],"document":{"id":"design-mc-gzh-05-rw2fmp","title":"新品正式发布","width":1800,"height":766,"background":{"gradient":"linear-gradient(155deg, #0b0f1a, #111827)","opacity":1,"overlay":"grid","overlayColor":"#22d3ee","overlayOpacity":0.08},"elements":[{"id":"shape-rw2fmp-1","type":"shape","x":1415.9200088554621,"y":-201.27957217119612,"w":823.7092410678553,"h":823.7092410678553,"rotation":0,"z":2,"locked":false,"opacity":0.5643030705229859,"props":{"kind":"circle","fill":"#1f2937","stroke":"transparent","strokeWidth":0,"radius":0}},{"id":"shape-rw2fmp-2","type":"shape","x":1171.8970198763054,"y":173.15289413163106,"w":801.2470641607638,"h":801.2470641607638,"rotation":0,"z":3,"locked":false,"opacity":0.5569852505144595,"props":{"kind":"circle","fill":"#f472b6","stroke":"transparent","strokeWidth":0,"radius":0}},{"id":"shape-rw2fmp-4","type":"shape","x":72,"y":45.96,"w":14.4,"h":14.4,"rotation":0,"z":3,"locked":false,"opacity":0.14,"props":{"kind":"circle","fill":"#22d3ee","stroke":"transparent","strokeWidth":0,"radius":0}},{"id":"shape-rw2fmp-5","type":"shape","x":153,"y":45.96,"w":14.4,"h":14.4,"rotation":0,"z":3,"locked":false,"opacity":0.14,"props":{"kind":"circle","fill":"#22d3ee","stroke":"transparent","strokeWidth":0,"radius":0}},{"id":"shape-rw2fmp-6","type":"shape","x":234,"y":45.96,"w":14.4,"h":14.4,"rotation":0,"z":3,"locked":false,"opacity":0.14,"props":{"kind":"circle","fill":"#22d3ee","stroke":"transparent","strokeWidth":0,"radius":0}},{"id":"shape-rw2fmp-7","type":"shape","x":315,"y":45.96,"w":14.4,"h":14.4,"rotation":0,"z":3,"locked":false,"opacity":0.14,"props":{"kind":"circle","fill":"#22d3ee","stroke":"transparent","strokeWidth":0,"radius":0}},{"id":"shape-rw2fmp-8","type":"shape","x":72,"y":126.96000000000001,"w":14.4,"h":14.4,"rotation":0,"z":3,"locked":false,"opacity":0.14,"props":{"kind":"circle","fill":"#22d3ee","stroke":"transparent","strokeWidth":0,"radius":0}},{"id":"shape-rw2fmp-9","type":"shape","x":153,"y":126.96000000000001,"w":14.4,"h":14.4,"rotation":0,"z":3,"locked":false,"opacity":0.14,"props":{"kind":"circle","fill":"#22d3ee","stroke":"transparent","strokeWidth":0,"radius":0}},{"id":"shape-rw2fmp-a","type":"shape","x":234,"y":126.96000000000001,"w":14.4,"h":14.4,"rotation":0,"z":3,"locked":false,"opacity":0.14,"props":{"kind":"circle","fill":"#22d3ee","stroke":"transparent","strokeWidth":0,"radius":0}},{"id":"shape-rw2fmp-b","type":"shape","x":315,"y":126.96000000000001,"w":14.4,"h":14.4,"rotation":0,"z":3,"locked":false,"opacity":0.14,"props":{"kind":"circle","fill":"#22d3ee","stroke":"transparent","strokeWidth":0,"radius":0}},{"id":"shape-rw2fmp-c","type":"shape","x":72,"y":207.96,"w":14.4,"h":14.4,"rotation":0,"z":3,"locked":false,"opacity":0.14,"props":{"kind":"circle","fill":"#22d3ee","stroke":"transparent","strokeWidth":0,"radius":0}},{"id":"shape-rw2fmp-d","type":"shape","x":153,"y":207.96,"w":14.4,"h":14.4,"rotation":0,"z":3,"locked":false,"opacity":0.14,"props":{"kind":"circle","fill":"#22d3ee","stroke":"transparent","strokeWidth":0,"radius":0}},{"id":"shape-rw2fmp-e","type":"shape","x":234,"y":207.96,"w":14.4,"h":14.4,"rotation":0,"z":3,"locked":false,"opacity":0.14,"props":{"kind":"circle","fill":"#22d3ee","stroke":"transparent","strokeWidth":0,"radius":0}},{"id":"shape-rw2fmp-f","type":"shape","x":315,"y":207.96,"w":14.4,"h":14.4,"rotation":0,"z":3,"locked":false,"opacity":0.14,"props":{"kind":"circle","fill":"#22d3ee","stroke":"transparent","strokeWidth":0,"radius":0}},{"id":"shape-rw2fmp-g","type":"shape","x":1404,"y":551.52,"w":14.4,"h":14.4,"rotation":0,"z":3,"locked":false,"opacity":0.14,"props":{"kind":"circle","fill":"#22d3ee","stroke":"transparent","strokeWidth":0,"radius":0}},{"id":"shape-rw2fmp-h","type":"shape","x":1485,"y":551.52,"w":14.4,"h":14.4,"rotation":0,"z":3,"locked":false,"opacity":0.14,"props":{"kind":"circle","fill":"#22d3ee","stroke":"transparent","strokeWidth":0,"radius":0}},{"id":"shape-rw2fmp-i","type":"shape","x":1566,"y":551.52,"w":14.4,"h":14.4,"rotation":0,"z":3,"locked":false,"opacity":0.14,"props":{"kind":"circle","fill":"#22d3ee","stroke":"transparent","strokeWidth":0,"radius":0}},{"id":"shape-rw2fmp-j","type":"shape","x":1647,"y":551.52,"w":14.4,"h":14.4,"rotation":0,"z":3,"locked":false,"opacity":0.14,"props":{"kind":"circle","fill":"#22d3ee","stroke":"transparent","strokeWidth":0,"radius":0}},{"id":"shape-rw2fmp-k","type":"shape","x":1404,"y":632.52,"w":14.4,"h":14.4,"rotation":0,"z":3,"locked":false,"opacity":0.14,"props":{"kind":"circle","fill":"#22d3ee","stroke":"transparent","strokeWidth":0,"radius":0}},{"id":"shape-rw2fmp-l","type":"shape","x":1485,"y":632.52,"w":14.4,"h":14.4,"rotation":0,"z":3,"locked":false,"opacity":0.14,"props":{"kind":"circle","fill":"#22d3ee","stroke":"transparent","strokeWidth":0,"radius":0}},{"id":"shape-rw2fmp-m","type":"shape","x":1566,"y":632.52,"w":14.4,"h":14.4,"rotation":0,"z":3,"locked":false,"opacity":0.14,"props":{"kind":"circle","fill":"#22d3ee","stroke":"transparent","strokeWidth":0,"radius":0}},{"id":"shape-rw2fmp-n","type":"shape","x":1647,"y":632.52,"w":14.4,"h":14.4,"rotation":0,"z":3,"locked":false,"opacity":0.14,"props":{"kind":"circle","fill":"#22d3ee","stroke":"transparent","strokeWidth":0,"radius":0}},{"id":"shape-rw2fmp-o","type":"shape","x":1404,"y":713.52,"w":14.4,"h":14.4,"rotation":0,"z":3,"locked":false,"opacity":0.14,"props":{"kind":"circle","fill":"#22d3ee","stroke":"transparent","strokeWidth":0,"radius":0}},{"id":"shape-rw2fmp-p","type":"shape","x":1485,"y":713.52,"w":14.4,"h":14.4,"rotation":0,"z":3,"locked":false,"opacity":0.14,"props":{"kind":"circle","fill":"#22d3ee","stroke":"transparent","strokeWidth":0,"radius":0}},{"id":"shape-rw2fmp-q","type":"shape","x":1566,"y":713.52,"w":14.4,"h":14.4,"rotation":0,"z":3,"locked":false,"opacity":0.14,"props":{"kind":"circle","fill":"#22d3ee","stroke":"transparent","strokeWidth":0,"radius":0}},{"id":"shape-rw2fmp-r","type":"shape","x":1647,"y":713.52,"w":14.4,"h":14.4,"rotation":0,"z":3,"locked":false,"opacity":0.14,"props":{"kind":"circle","fill":"#22d3ee","stroke":"transparent","strokeWidth":0,"radius":0}},{"id":"shape-rw2fmp-s","type":"shape","x":1404,"y":794.52,"w":14.4,"h":14.4,"rotation":0,"z":3,"locked":false,"opacity":0.14,"props":{"kind":"circle","fill":"#22d3ee","stroke":"transparent","strokeWidth":0,"radius":0}},{"id":"shape-rw2fmp-t","type":"shape","x":1485,"y":794.52,"w":14.4,"h":14.4,"rotation":0,"z":3,"locked":false,"opacity":0.14,"props":{"kind":"circle","fill":"#22d3ee","stroke":"transparent","strokeWidth":0,"radius":0}},{"id":"shape-rw2fmp-u","type":"shape","x":1566,"y":794.52,"w":14.4,"h":14.4,"rotation":0,"z":3,"locked":false,"opacity":0.14,"props":{"kind":"circle","fill":"#22d3ee","stroke":"transparent","strokeWidth":0,"radius":0}},{"id":"shape-rw2fmp-v","type":"shape","x":1647,"y":794.52,"w":14.4,"h":14.4,"rotation":0,"z":3,"locked":false,"opacity":0.14,"props":{"kind":"circle","fill":"#22d3ee","stroke":"transparent","strokeWidth":0,"radius":0}},{"id":"shape-rw2fmp-3","type":"shape","x":1046.2274670765864,"y":460.54475909273356,"w":710.9942076480921,"h":710.9942076480921,"rotation":0,"z":4,"locked":false,"opacity":0.7754571712927227,"props":{"kind":"circle","fill":"#22d3ee","stroke":"transparent","strokeWidth":0,"radius":0}},{"id":"shape-rw2fmp-w","type":"shape","x":0,"y":0,"w":1800,"h":122.56,"rotation":0,"z":8,"locked":false,"opacity":1,"props":{"kind":"rect","fill":"rgba(34,211,238,0.92)","stroke":"transparent","strokeWidth":0,"radius":0}},{"id":"text-rw2fmp-x","type":"text","x":72,"y":22.98,"w":1080,"h":76.60000000000001,"rotation":0,"z":12,"locked":false,"opacity":1,"props":{"text":"海豚科技","fontSize":68.94,"color":"#0b0f1a","fontFamily":"Alibaba PuHuiTi","fontWeight":800,"fontStyle":"normal","lineHeight":1.12,"letterSpacing":0,"textAlign":"left","effect":"none"}},{"id":"shape-rw2fmp-11","type":"shape","x":1296,"y":153.20000000000002,"w":459.59999999999997,"h":459.59999999999997,"rotation":0,"z":20,"locked":false,"opacity":0.9,"props":{"kind":"circle","fill":"#f472b6","stroke":"transparent","strokeWidth":0,"radius":0}},{"id":"shape-rw2fmp-12","type":"shape","x":1368,"y":214.48000000000002,"w":337.04,"h":337.04,"rotation":0,"z":21,"locked":false,"opacity":1,"props":{"kind":"circle","fill":"transparent","stroke":"rgba(255,255,255,0.7)","strokeWidth":4,"radius":0}},{"id":"text-rw2fmp-13","type":"text","x":1296,"y":245.12,"w":459.59999999999997,"h":275.76,"rotation":0,"z":22,"locked":false,"opacity":1,"props":{"text":"品","fontSize":245.12,"color":"#ffffff","fontFamily":"YouSheBiaoTiHei","fontWeight":900,"fontStyle":"normal","lineHeight":1.12,"letterSpacing":0,"textAlign":"center","effect":"none"}},{"id":"text-rw2fmp-y","type":"text","x":108,"y":153.20000000000002,"w":306.37410714285704,"h":144.630375,"rotation":0,"z":30,"locked":false,"opacity":1,"props":{"text":"新品","fontSize":129.94642857142853,"color":"#0b0f1a","fontFamily":"Alibaba PuHuiTi","fontWeight":900,"fontStyle":"normal","lineHeight":1.06,"letterSpacing":1,"textAlign":"left","effect":"highlight","highlightColor":"#22d3ee"}},{"id":"text-rw2fmp-z","type":"text","x":108,"y":290.94321428571425,"w":1116,"h":144.630375,"rotation":0,"z":30,"locked":false,"opacity":1,"props":{"text":"正式发布","fontSize":129.94642857142853,"color":"#f0f9ff","fontFamily":"Alibaba PuHuiTi","fontWeight":900,"fontStyle":"normal","lineHeight":1.06,"letterSpacing":1,"textAlign":"left","effect":"none"}},{"id":"text-rw2fmp-10","type":"text","x":108,"y":449.47785714285703,"w":1116,"h":99.58,"rotation":0,"z":30,"locked":false,"opacity":1,"props":{"text":"重新定义你的效率工具","fontSize":68.94,"color":"#a5b4fc","fontFamily":"Alibaba PuHuiTi","fontWeight":700,"fontStyle":"normal","lineHeight":1.12,"letterSpacing":0,"textAlign":"left","effect":"none"}}],"updatedAt":"2026-07-04T09:30:01.547Z"}}