{"spec":{"id":"re-car-festival","industry":"房地产","channel":"社群朋友圈","material":"方形海报","title":"购车狂欢一价到底","style":"promo-price"},"attributions":[],"document":{"id":"design-re-car-festival-zau1wa","title":"购车狂欢一价到底","width":1080,"height":1080,"background":{"gradient":"linear-gradient(155deg, #0f172a, #1e293b)","opacity":1},"elements":[{"id":"shape-zau1wa-1","type":"shape","x":0,"y":0,"w":1080,"h":1080,"rotation":0,"z":1,"locked":false,"opacity":1,"props":{"kind":"rect","fill":"transparent","stroke":"transparent","strokeWidth":0,"radius":0}},{"id":"shape-zau1wa-2","type":"shape","x":-108,"y":-108,"w":1404,"h":540,"rotation":-6,"z":2,"locked":false,"opacity":0.9,"props":{"kind":"rect","fill":"#f59e0b","stroke":"transparent","strokeWidth":0,"radius":0}},{"id":"shape-zau1wa-3","type":"shape","x":669.6,"y":21.6,"w":540,"h":540,"rotation":0,"z":3,"locked":false,"opacity":0.18,"props":{"kind":"circle","fill":"#fcd34d","stroke":"transparent","strokeWidth":0,"radius":0}},{"id":"image-zau1wa-9","type":"image","x":496.8,"y":367.20000000000005,"w":540,"h":540,"rotation":0,"z":20,"locked":false,"opacity":1,"props":{"src":"https://oceanleo-assets.oss-cn-guangzhou.aliyuncs.com/assets/image/design-object/design-obj-carkey-01.webp?x-oss-process=image/format,png","radius":0,"filter":"none","flipX":false,"flipY":false}},{"id":"text-zau1wa-6","type":"text","x":75.60000000000001,"y":97.2,"w":756,"h":113.4,"rotation":0,"z":30,"locked":false,"opacity":1,"props":{"text":"购车狂欢","fontSize":108,"color":"#111827","fontFamily":"system-ui","fontWeight":900,"fontStyle":"normal","lineHeight":1.12,"letterSpacing":0,"textAlign":"left","effect":"shadow"}},{"id":"text-zau1wa-7","type":"text","x":75.60000000000001,"y":210.60000000000002,"w":756,"h":113.4,"rotation":0,"z":30,"locked":false,"opacity":1,"props":{"text":"一价到底","fontSize":108,"color":"#111827","fontFamily":"system-ui","fontWeight":900,"fontStyle":"normal","lineHeight":1.12,"letterSpacing":0,"textAlign":"left","effect":"shadow"}},{"id":"text-zau1wa-8","type":"text","x":75.60000000000001,"y":328,"w":756,"h":64.8,"rotation":0,"z":30,"locked":false,"opacity":1,"props":{"text":"限时厂补 至高钜惠","fontSize":43.2,"color":"#111827","fontFamily":"system-ui","fontWeight":700,"fontStyle":"normal","lineHeight":1.12,"letterSpacing":0,"textAlign":"left","effect":"none"}},{"id":"text-zau1wa-a","type":"text","x":75.60000000000001,"y":648,"w":432,"h":64.8,"rotation":0,"z":30,"locked":false,"opacity":1,"props":{"text":"至高综合优惠","fontSize":43.2,"color":"#f59e0b","fontFamily":"system-ui","fontWeight":800,"fontStyle":"normal","lineHeight":1.12,"letterSpacing":0,"textAlign":"left","effect":"none"}},{"id":"text-zau1wa-f","type":"text","x":648,"y":1015.1999999999999,"w":367.20000000000005,"h":43.2,"rotation":0,"z":30,"locked":false,"opacity":0.9,"props":{"text":"到店礼遇 · 名额有限","fontSize":28.08,"color":"#111827","fontFamily":"system-ui","fontWeight":600,"fontStyle":"normal","lineHeight":1.12,"letterSpacing":0,"textAlign":"right","effect":"none"}},{"id":"text-zau1wa-b","type":"text","x":75.60000000000001,"y":756,"w":129.6,"h":151.20000000000002,"rotation":0,"z":31,"locked":false,"opacity":1,"props":{"text":"万","fontSize":108,"color":"#d97706","fontFamily":"system-ui","fontWeight":900,"fontStyle":"normal","lineHeight":1.12,"letterSpacing":0,"textAlign":"left","effect":"none"}},{"id":"text-zau1wa-c","type":"text","x":183.60000000000002,"y":669.6,"w":648,"h":324,"rotation":0,"z":31,"locked":false,"opacity":1,"props":{"text":"3","fontSize":345.6,"color":"#d97706","fontFamily":"system-ui","fontWeight":900,"fontStyle":"normal","lineHeight":1.12,"letterSpacing":-4,"textAlign":"left","effect":"none"}},{"id":"shape-zau1wa-d","type":"shape","x":75.60000000000001,"y":972,"w":540,"h":84,"rotation":0,"z":39,"locked":false,"opacity":1,"props":{"kind":"rect","fill":"#d97706","stroke":"transparent","strokeWidth":0,"radius":42,"shadowPreset":"medium"}},{"id":"text-zau1wa-e","type":"text","x":75.60000000000001,"y":990,"w":540,"h":52,"rotation":0,"z":40,"locked":false,"opacity":1,"props":{"text":"预约试驾","fontSize":40,"color":"#ffffff","fontFamily":"system-ui","fontWeight":900,"fontStyle":"normal","lineHeight":1.12,"letterSpacing":0,"textAlign":"center","effect":"none"}},{"id":"shape-zau1wa-4","type":"shape","x":756,"y":32.4,"w":280.8,"h":280.8,"rotation":-8,"z":42,"locked":false,"opacity":1,"props":{"kind":"star","fill":"#fcd34d","stroke":"transparent","strokeWidth":0,"radius":0}},{"id":"text-zau1wa-5","type":"text","x":800.928,"y":127.87200000000001,"w":190.94400000000002,"h":84.24,"rotation":-8,"z":43,"locked":false,"opacity":1,"props":{"text":"购车节","fontSize":52,"color":"#f8fafc","fontFamily":"system-ui","fontWeight":900,"fontStyle":"normal","lineHeight":1.12,"letterSpacing":0,"textAlign":"center","effect":"none"}}],"updatedAt":"2026-07-03T19:51:41.603Z"}}